COPYING
COPYING.lesser
MANIFEST.in
NOTICE
README.md
requirements.txt
setup.cfg
setup.py
compiler/__init__.py
compiler/api/__init__.py
compiler/api/compiler.py
compiler/api/source/auth_key.tl
compiler/api/source/main_api.tl
compiler/api/source/sys_msgs.tl
compiler/api/template/combinator.txt
compiler/api/template/type.txt
compiler/docs/__init__.py
compiler/docs/compiler.py
compiler/docs/template/page.txt
compiler/docs/template/toctree.txt
compiler/errors/__init__.py
compiler/errors/compiler.py
compiler/errors/sort.py
compiler/errors/source/303_SEE_OTHER.tsv
compiler/errors/source/400_BAD_REQUEST.tsv
compiler/errors/source/401_UNAUTHORIZED.tsv
compiler/errors/source/403_FORBIDDEN.tsv
compiler/errors/source/406_NOT_ACCEPTABLE.tsv
compiler/errors/source/420_FLOOD.tsv
compiler/errors/source/500_INTERNAL_SERVER_ERROR.tsv
compiler/errors/source/503_SERVICE_UNAVAILABLE.tsv
compiler/errors/template/class.txt
compiler/errors/template/sub_class.txt
py_Pyro.egg-info/PKG-INFO
py_Pyro.egg-info/SOURCES.txt
py_Pyro.egg-info/dependency_links.txt
py_Pyro.egg-info/not-zip-safe
py_Pyro.egg-info/requires.txt
py_Pyro.egg-info/top_level.txt
pyro/__init__.py
pyro/client.py
pyro/dispatcher.py
pyro/emoji.py
pyro/file_id.py
pyro/filters.py
pyro/mime_types.py
pyro/py.typed
pyro/scaffold.py
pyro/sync.py
pyro/syncer.py
pyro/utils.py
pyro/connection/__init__.py
pyro/connection/connection.py
pyro/connection/transport/__init__.py
pyro/connection/transport/tcp/__init__.py
pyro/connection/transport/tcp/tcp.py
pyro/connection/transport/tcp/tcp_abridged.py
pyro/connection/transport/tcp/tcp_abridged_o.py
pyro/connection/transport/tcp/tcp_full.py
pyro/connection/transport/tcp/tcp_intermediate.py
pyro/connection/transport/tcp/tcp_intermediate_o.py
pyro/crypto/__init__.py
pyro/crypto/aes.py
pyro/crypto/mtproto.py
pyro/crypto/prime.py
pyro/crypto/rsa.py
pyro/errors/__init__.py
pyro/errors/rpc_error.py
pyro/handlers/__init__.py
pyro/handlers/callback_query_handler.py
pyro/handlers/chat_join_request_handler.py
pyro/handlers/chat_member_updated_handler.py
pyro/handlers/chosen_inline_result_handler.py
pyro/handlers/deleted_messages_handler.py
pyro/handlers/disconnect_handler.py
